{
  "individu": {
    "fields": [
      {
        "label": "Photo, image",
        "data-property": "foaf:img",
        "type": "url"
      },
      {
        "label": "Nom",
        "data-property": "foaf:name",
      },
      {
        "label": "Description courte (140 caractères max)",
        "data-property": "pair:shortDescription",
        "type": "textarea"
      },
      {
        "label": "Prénom",
        "data-property": "foaf:firstName",
      },
      {
        "label": "Pseudonyme",
        "data-property": "foaf:nick",
      },
      {
        "label": "Code postal",
        "data-property": "pair:zipCode",
        "type": "zipcode"
      },
      {
        "label": "Ville",
        "data-property": "pair:town",
      },
      {
        "label": "Pays",
        "data-property": "pair:country",
      },
      {
        "label": "Email",
        "data-property": "foaf:mbox",
        "type": "url"
      },
      {
        "label": "Site ou page web",
        "data-property": "foaf:weblog",
        "type": "url"
      },
      {
        "label": "Réseau social 1",
        "data-property": "pair:socialNetworks",
        "type": "url"
      },
      {
        "label": "Réseau social 2",
        "data-property": "pair:socialNetworks",
        "type": "url"
      },
      {
        "label": "Réseau social 3",
        "data-property": "pair:socialNetworks",
        "type": "url"
      },
      {
        "label": "Description (1000 caractères max)",
        "data-property": "pair:description",
        "type": "textarea"
      },
      {
        "label": "Description longue (illimité)",
        "data-property": "pair:longDescription",
        "type": "textarea"
      },
      {
        "label": "Projet 1 auxquel vous contribuez",
        "object-property": "foaf:currentProject",
        "range": "foaf:Project",
        "type": "resource"
      },
      {
        "label": "Projet 2 auxquel vous contribuez",
        "object-property": "foaf:currentProject",
        "range": "foaf:Project",
        "type": "resource"
      },
      {
        "label": "Projet 3 auxquel vous contribuez",
        "object-property": "foaf:currentProject",
        "range": "foaf:Project",
        "type": "resource"
      },
      {
        "label": "Projet 1 que vous soutenez",
        "object-property": "pair:supports",
        "range": "foaf:Project",
        "type": "resource"
      },
      {
        "label": "Projet 2 que vous soutenez",
        "object-property": "pair:supports",
        "range": "foaf:Project",
        "type": "resource"
      },
      {
        "label": "Projet 3 que vous soutenez",
        "object-property": "pair:supports",
        "range": "foaf:Project",
        "type": "resource"
      },
      {
        "label": "Ami 1",
        "object-property": "pair:isFriendOf",
        "range": "foaf:person",
        "type": "resource"
      },
      {
        "label": "Ami 2",
        "object-property": "pair:isFriendOf",
        "range": "foaf:person",
        "type": "resource"
      },
      {
        "label": "Ami 3",
        "object-property": "pair:isFriendOf",
        "range" : "foaf:person",
        "type": "resource"
      },
      {
        "label": "Collaborateur 1",
        "object-property": "pair:worksWith",
        "range": "foaf:person",
        "type": "resource"
      },
      {
        "label": "Collaborateur 2",
        "object-property": "pair:worksWith",
        "range": "foaf:person",
        "type": "resource"
      },
      {
        "label": "Collaborateur 3",
        "object-property": "pair:worksWith",
        "range": "foaf:person",
        "type": "resource"
      },
      {
        "label": "Collaborateur 4",
        "object-property": "pair:worksWith",
        "range": "foaf:person",
        "type": "resource"
      },
      {
       "label": "Collaborateur 5",
        "object-property": "pair:worksWith",
        "range": "foaf:person",
        "type": "resource"
      },
      {
        "label": "Organisation dans laquelle vous êtes employé(e)",
        "object-property": "pair:employee",
        "range": "foaf:organization",
        "type": "resource"
      },
      {
        "label": "Organisation 1 dans laquelle vous exercez des responsabilités",
        "object-property": "pair:employee",
        "range": "foaf:organization",
        "type": "resource"
      },
      {
        "label": "Organisation 2 dans laquelle vous exercez des responsabilités",
        "object-property": "pair:employee",
        "range": "foaf:organization",
        "type": "resource"
      },
      {
        "label": "Organisation 1 à laquelle vous contribuez",
        "object-property": "pair:contributesTo",
        "range": "foaf:organization",
        "type": "resource"
      },
      {
        "label": "Organisation 2 à laquelle vous contribuez",
        "object-property": "pair:contributesTo",
        "range": "foaf:organization",
        "type": "resource"
      },
      {
        "label": "Centre d'intérêt 1",
        "object-property": "dcterms:subject",
        "range": "pair:idea",
        "type": "resource"
      },
      {
        "label": "Centre d'intérêt 2",
        "object-property": "dcterms:subject",
        "range": "pair:idea",
        "type": "resource"
      },
      {
        "label": "Centre d'intérêt 3",
        "object-property": "dcterms:subject",
        "range": "pair:idea",
        "type": "resource"
      },
      {
        "label": "Centre d'intérêt 4",
        "object-property": "dcterms:subject",
        "range": "pair:idea",
        "type": "resource"
      },
      {
        "label": "Centre d'intérêt 5",
        "object-property": "dcterms:subject",
        "range": "pair:idea",
        "type": "resource"
      },
      {
        "label": "Centre d'intérêt 6",
        "object-property": "dcterms:subject",
        "range": "pair:idea",
        "type": "resource"
      },
      {
        "label": "Besoin de compétence 1",
        "object-property": "gr:seeks",
        "range": "cco:skill",
        "type": "resource"
      },
      {
        "label": "Besoin de compétence 2",
        "object-property": "gr:seeks",
        "range": "cco:skill",
        "type": "resource"
      },
      {
        "label" : "Besoin de ressource 1 (hors compétences)",
        "object-property": "gr:seeks",
        "range": "pair:resource",
        "type": "resource"
      },
      {
        "label": "Besoin de ressource 2 (hors compétences)",
        "object-property": "gr:seeks",
        "range": "pair:resource",
        "type": "resource"
      },
      {
        "label": "Offre de compétence 1",
        "object-property": "gr:offers",
        "range": "cco:skill",
        "type": "resource"
      },
      {
        "label": "Offre de compétence 2",
        "object-property": "gr:offers",
        "range": "cco:skill",
        "type": "resource"
      },
      {
        "label": "Offre de ressource 1 (hors compétences)",
        "object-property": "gr:offers",
        "range": "pair:resource",
        "type": "resource"
      },
      {
        "label": "Offre de ressource 1 (hors compétences)",
        "object-property": "gr:offers",
        "range": "pair:resource",
        "type": "resource"
      },
    ]
  }
}
